Metadata-Version: 2.1
Name: mrz-surepass
Version: 0.6.4
Summary: Machine readable zone generator and checker for passports, visas, id cards and other travel documents
Home-page: https://github.com/surepassio/mrz-surepass
Author: Rishabh Chauhan
Author-email: rc@surepass.io
License: GPLv3
Keywords: mrz passports visas id cards td1 td2 td3 mrva mrvb icao
Classifier: Development Status :: 4 - Beta
Classifier: License :: OSI Approved :: GNU General Public License v3 (GPLv3)
Classifier: Programming Language :: Python :: 3.6
Classifier: Programming Language :: Python :: 3.7
Classifier: Programming Language :: Python :: 3.8
Classifier: Programming Language :: Python :: 3.9
Classifier: Programming Language :: Python :: 3.10
Classifier: Topic :: Security
License-File: LICENSE
